tests/__init__.py
tests/test_datasets.py
tests/test_preprocessing.py
tests/test_rapidoml.py
rapidoml-0.1.3.dist-info/LICENSE
rapidoml-0.1.3.dist-info/METADATA
rapidoml-0.1.3.dist-info/WHEEL
rapidoml-0.1.3.dist-info/top_level.txt
rapidoml-0.1.3.dist-info/RECORD
