Metadata-Version: 2.1
Name: rapidoml
Version: 0.1.3
Summary: RapidoML is a simple Automated Machine Learning (AutoML) library
Home-page: https://github.com/hipnologo/rapidoml
Author: Fabio Carvalho
Author-email: Fabio Carvalho <hipnologo@gmail.com>
License: Apache License
Project-URL: Homepage, https://github.com/hipnologo/rapidoml
Project-URL: Bug Tracker, https://github.com/hipnologo/rapidoml/issues
Keywords: documentation,python
Classifier: Development Status :: 3 - Alpha
Classifier: Intended Audience :: Developers
Classifier: License :: OSI Approved :: Apache Software License
Classifier: Programming Language :: Python :: 3
Classifier: Programming Language :: Python :: 3.6
Classifier: Programming Language :: Python :: 3.7
Classifier: Programming Language :: Python :: 3.8
Classifier: Programming Language :: Python :: 3.9
License-File: LICENSE
Requires-Dist: numpy
Requires-Dist: scikit-learn
Requires-Dist: tensorflow
Requires-Dist: keras
Requires-Dist: xgboost
Requires-Dist: lightgbm
Requires-Dist: catboost
